sanlogger/__init__.py
sanlogger/config.py
sanlogger/config_utilities/__init__.py
sanlogger/config_utilities/yaml_utils.py
sanlogger/logging/__init__.py
sanlogger/logging/handlers/__init__.py
sanlogger/logging/handlers/base_handler.py
sanlogger/logging/handlers/console_handler.py
sanlogger/logging/handlers/file_handler.py
sanlogger/paths.py
sanlogger-0.1.0.dist-info/LICENSE
sanlogger-0.1.0.dist-info/METADATA
sanlogger-0.1.0.dist-info/WHEEL
sanlogger-0.1.0.dist-info/RECORD
